
{
	"name": "The xxxx is an NFT",
	"description": "H is for hanjin… H is also for human beings, happiness and hope! The black background represents the great unknown of the blockchain and NFT space. The ever changing colors represent the limitless imagination and hope that resides in each and every one of us! If we stay positive and work hard at it, we can light up this space and usher in a better tomorrow for everyone!",
	"video":"https://raw.githubusercontent.com/nft-artist/nft/master/chr/1.mp4",
	"external_url":"https://raw.githubusercontent.com/nft-artist/nft/master/chr/1.json",
	"attributes":[]
}